<?xml version="1.0" encoding="utf-8"?>
<doctrine-mapping xmlns="http://doctrine-project.org/schemas/orm/doctrine-mapping" xmlns:xsi="http://www.w3.org/2001/XMLSchema-instance" xsi:schemaLocation="http://doctrine-project.org/schemas/orm/doctrine-mapping http://doctrine-project.org/schemas/orm/doctrine-mapping.xsd">
  <entity name="AppShopRegister" table="app_shop_register">
    <id name="id" type="integer" column="id">
      <generator strategy="IDENTITY"/>
    </id>
    <field name="processflag" type="text" column="processflag" nullable="true">
      <options>
        <option name="fixed"/>
      </options>
    </field>
    <field name="insertPlatform" type="text" column="insert_platform" nullable="true">
      <options>
        <option name="fixed"/>
        <option name="default">1</option>
      </options>
    </field>
    <field name="insertUser" type="text" column="insert_user" nullable="true">
      <options>
        <option name="fixed"/>
      </options>
    </field>
    <field name="insertDate" type="text" column="insert_date" nullable="true">
      <options>
        <option name="fixed"/>
      </options>
    </field>
    <field name="updatePlatform" type="text" column="update_platform" nullable="true">
      <options>
        <option name="fixed"/>
        <option name="default">1</option>
      </options>
    </field>
    <field name="updateUser" type="text" column="update_user" nullable="true">
      <options>
        <option name="fixed"/>
      </options>
    </field>
    <field name="updateDate" type="text" column="update_date" nullable="true">
      <options>
        <option name="fixed"/>
      </options>
    </field>
    <field name="isErpsent" type="text" column="is_erpsent" nullable="true">
      <options>
        <option name="fixed"/>
      </options>
    </field>
    <field name="isEnabled" type="text" column="is_enabled" nullable="true">
      <options>
        <option name="fixed"/>
        <option name="default">1</option>
      </options>
    </field>
    <field name="i" type="integer" column="i" nullable="true">
      <options>
        <option name="unsigned"/>
      </options>
    </field>
    <field name="codeErp" type="text" column="code_erp" nullable="true">
      <options>
        <option name="fixed"/>
      </options>
    </field>
    <field name="description" type="text" column="description" nullable="true">
      <options>
        <option name="fixed"/>
      </options>
    </field>
    <field name="remoteIp" type="text" column="remote_ip" nullable="true">
      <options>
        <option name="fixed"/>
      </options>
    </field>
    <field name="tokenactivate" type="text" column="tokenactivate" nullable="true">
      <options>
        <option name="fixed"/>
      </options>
    </field>
    <field name="idTypeProcess" type="integer" column="id_type_process" nullable="true">
      <options>
        <option name="unsigned"/>
      </options>
    </field>
    <field name="idTypeGender" type="integer" column="id_type_gender" nullable="true">
      <options>
        <option name="unsigned"/>
      </options>
    </field>
    <field name="firstName" type="text" column="first_name" nullable="true">
      <options>
        <option name="fixed"/>
      </options>
    </field>
    <field name="lastName1" type="text" column="last_name_1" nullable="true">
      <options>
        <option name="fixed"/>
      </options>
    </field>
    <field name="lastName2" type="text" column="last_name_2" nullable="true">
      <options>
        <option name="fixed"/>
      </options>
    </field>
    <field name="birthdate" type="text" column="birthdate" nullable="true">
      <options>
        <option name="fixed"/>
      </options>
    </field>
    <field name="howMeetus" type="text" column="how_meetus" nullable="true">
      <options>
        <option name="fixed"/>
      </options>
    </field>
    <field name="login" type="text" column="login" nullable="true">
      <options>
        <option name="fixed"/>
      </options>
    </field>
    <field name="password" type="text" column="password" nullable="true">
      <options>
        <option name="fixed"/>
      </options>
    </field>
    <field name="isRobinsonEmail" type="text" column="is_robinson_email" nullable="true">
      <options>
        <option name="fixed"/>
      </options>
    </field>
    <field name="isPolicy" type="text" column="is_policy" nullable="true">
      <options>
        <option name="fixed"/>
      </options>
    </field>
  </entity>
</doctrine-mapping>
